mlsysops/__init__.py
mlsysops/agent.py
mlsysops/application.py
mlsysops/events.py
mlsysops/logger_util.py
mlsysops/policy.py
mlsysops/scheduler.py
mlsysops/utilities.py
mlsysops/assets/__init__.py
mlsysops/assets/assets.py
mlsysops/classes/__init__.py
mlsysops/controllers/__init__.py
mlsysops/controllers/application.py
mlsysops/controllers/base.py
mlsysops/controllers/configuration.py
mlsysops/controllers/mechanisms.py
mlsysops/controllers/policy.py
mlsysops/controllers/telemetry.py
mlsysops/controllers/libs/__init__.py
mlsysops/controllers/libs/otel_pods.py
mlsysops/data/__init__.py
mlsysops/data/configuration.py
mlsysops/data/monitor.py
mlsysops/data/plan.py
mlsysops/data/state.py
mlsysops/data/task_log.py
mlsysops/policies/policy-cluster-dynamicPlacement.py
mlsysops/policies/policy-cluster-staticPlacement.py
mlsysops/spade/__init__.py
mlsysops/spade/mls_spade.py
mlsysops/spade/redis_mgt.py
mlsysops/spade/behaviors/APIPingBehaviour.py
mlsysops/spade/behaviors/CheckInactiveClustersBehaviour.py
mlsysops/spade/behaviors/CheckInactiveNodesBehaviour.py
mlsysops/spade/behaviors/Check_ml_deployment_Behaviour.py
mlsysops/spade/behaviors/FailoverBehaviour.py
mlsysops/spade/behaviors/HBRecieverBehaviour.py
mlsysops/spade/behaviors/HeartbeatBehavior.py
mlsysops/spade/behaviors/ML_process_Behaviour.py
mlsysops/spade/behaviors/ManageSubscriptionBehaviour.py
mlsysops/spade/behaviors/ManagementModeBehaviour.py
mlsysops/spade/behaviors/MessageReceivingBehavior.py
mlsysops/spade/behaviors/MessageSendingBehavior.py
mlsysops/spade/behaviors/ProcessBehaviour.py
mlsysops/spade/behaviors/SubscribeBehavior.py
mlsysops/spade/behaviors/__init__.py
mlsysops/tasks/__init__.py
mlsysops/tasks/analyze.py
mlsysops/tasks/base.py
mlsysops/tasks/execute.py
mlsysops/tasks/monitor.py
mlsysops/tasks/plan.py
mlsysops/templates/node-exporter-pod-definition.yml.j2
mlsysops/templates/otel-collector-pod-definition.yml.j2
mlsysops/templates/otel-collector-service.yaml.j2
mlsysops-0.1.11.dist-info/licenses/LICENSE
mlsysops-0.1.11.dist-info/METADATA
mlsysops-0.1.11.dist-info/WHEEL
mlsysops-0.1.11.dist-info/top_level.txt
mlsysops-0.1.11.dist-info/RECORD
