Metadata-Version: 2.4
Name: mlsysops
Version: 0.1.11
Summary: The core python package for MLSysOps Agents Framework.
Home-page: https://github.com/mlsysops-project/mlsysops-framework
Author: MLSysOps Project Consortium
Author-email: info@mlsysops.eu
License: Apache License 2.0
Classifier: Development Status :: 3 - Alpha
Classifier: Intended Audience :: Developers
Classifier: Programming Language :: Python :: 3
Classifier: Programming Language :: Python :: 3.10
License-File: LICENSE
Requires-Dist: numpy>=1.20
Requires-Dist: pandas==2.2.3
Requires-Dist: spade==3.3.3
Requires-Dist: jinja2==3.0.3
Requires-Dist: kubernetes==32.0.1
Requires-Dist: kubernetes_asyncio==32.0.0
Requires-Dist: mlstelemetry==0.3.2
Requires-Dist: python-dotenv==1.1.0
Requires-Dist: PyYAML==6.0.2
Requires-Dist: redis
Requires-Dist: ruamel.yaml
Requires-Dist: watchdog
Dynamic: author
Dynamic: author-email
Dynamic: classifier
Dynamic: description
Dynamic: description-content-type
Dynamic: home-page
Dynamic: license
Dynamic: license-file
Dynamic: requires-dist
Dynamic: summary
